sightseeingtech_passhub_api/__init__.py
sightseeingtech_passhub_api/api_client.py
sightseeingtech_passhub_api/configuration.py
sightseeingtech_passhub_api/rest.py
sightseeingtech_passhub_api/api/__init__.py
sightseeingtech_passhub_api/api/order_record_resource_api.py
sightseeingtech_passhub_api/api/product_resource_api.py
sightseeingtech_passhub_api/api/vendor_resource_api.py
sightseeingtech_passhub_api/api/voucher_resource_api.py
sightseeingtech_passhub_api/models/__init__.py
sightseeingtech_passhub_api/models/address.py
sightseeingtech_passhub_api/models/condition.py
sightseeingtech_passhub_api/models/delivery_dto.py
sightseeingtech_passhub_api/models/extra_validation_param_dto.py
sightseeingtech_passhub_api/models/generic_status_dto.py
sightseeingtech_passhub_api/models/group_entry_dto.py
sightseeingtech_passhub_api/models/json_object.py
sightseeingtech_passhub_api/models/map_ofstring_andstring.py
sightseeingtech_passhub_api/models/order_item.py
sightseeingtech_passhub_api/models/order_note_param_dto.py
sightseeingtech_passhub_api/models/order_record_dto.py
sightseeingtech_passhub_api/models/order_record_extend_dto.py
sightseeingtech_passhub_api/models/product_dto.py
sightseeingtech_passhub_api/models/product_suggestion.py
sightseeingtech_passhub_api/models/recharge_product_group.py
sightseeingtech_passhub_api/models/recharge_prompt.py
sightseeingtech_passhub_api/models/recharge_prompt_entry.py
sightseeingtech_passhub_api/models/rule.py
sightseeingtech_passhub_api/models/simple_connected_product_dto.py
sightseeingtech_passhub_api/models/simple_metadata.py
sightseeingtech_passhub_api/models/simple_product_connection_dto.py
sightseeingtech_passhub_api/models/simple_product_dto.py
sightseeingtech_passhub_api/models/suggested_order.py
sightseeingtech_passhub_api/models/suggested_order_item.py
sightseeingtech_passhub_api/models/universal_attribute.py
sightseeingtech_passhub_api/models/user_compact_dto.py
sightseeingtech_passhub_api-1.0.0.dist-info/METADATA
sightseeingtech_passhub_api-1.0.0.dist-info/RECORD
sightseeingtech_passhub_api-1.0.0.dist-info/WHEEL
sightseeingtech_passhub_api-1.0.0.dist-info/top_level.txt
