Metadata-Version: 2.1
Name: sightseeingtech-passhub-api
Version: 1.0.0
Summary: PassHub API Client
Home-page: https://github.com/BYMdevelopment/passhub-api-client-python
Author: BYM Development LLC
Author-email: dev@sightseeingtech.com
License: UNKNOWN
Keywords: PassHub,SightseeingPass,API Client,API
Platform: UNKNOWN
Classifier: Programming Language :: Python :: 3
Classifier: License :: OSI Approved :: MIT License
Classifier: Operating System :: OS Independent
Requires-Dist: urllib3 (>=1.15)
Requires-Dist: six (>=1.10)
Requires-Dist: certifi
Requires-Dist: python-dateutil
